LICENSE
wallger/__init__.py
wallger/__main__.py
wallger/constants.py
wallger/core.py
wallger/helpers.py
wallger/ui.py
wallger/wallhaven.py
wallger-1.2.0.dist-info/entry_points.txt
wallger-1.2.0.dist-info/LICENSE
wallger-1.2.0.dist-info/WHEEL
wallger-1.2.0.dist-info/METADATA
wallger-1.2.0.dist-info/RECORD
