Metadata-Version: 2.1
Name: wallger
Version: 1.2.0
Summary: Wallpaper changer for Linux, get images from Wallhaven, Unsplash and others!
Home-page: https://github.com/UltiRequiem/wallger
License: MIT
Keywords: commands,wallpapers,utilities,cli
Author: Eliaz Bobadilla
Author-email: eliaz.bobadilladev@gmail.com
Requires-Python: >=3.7,<4.0
Classifier: License :: OSI Approved :: MIT License
Classifier: Programming Language :: Python :: 3
Classifier: Programming Language :: Python :: 3.7
Classifier: Programming Language :: Python :: 3.8
Classifier: Programming Language :: Python :: 3.9
Requires-Dist: colorama (>=0.4.4,<0.5.0)
Requires-Dist: requests (>=2.26.0,<3.0.0)
Project-URL: Repository, https://github.com/UltiRequiem/wallger
